jsondict.py
setup.py
jsondict.egg-info/PKG-INFO
jsondict.egg-info/SOURCES.txt
jsondict.egg-info/dependency_links.txt
jsondict.egg-info/requires.txt
jsondict.egg-info/top_level.txt