Metadata-Version: 1.0
Name: jsondict
Version: 1.2
Summary: Dict with json file saving / restoring support
Home-page: https://github.com/imbolc/jsondict
Author: Imbolc
Author-email: imbolc@imbolc.name
License: ISC
Platform: UNKNOWN
Classifier: Development Status :: 4 - Beta
Classifier: Intended Audience :: Developers
Classifier: License :: OSI Approved :: ISC License (ISCL)
Classifier: Programming Language :: Python
